laziter.py
laziter-0.0.6.dist-info/LICENSE
laziter-0.0.6.dist-info/METADATA
laziter-0.0.6.dist-info/WHEEL
laziter-0.0.6.dist-info/top_level.txt
laziter-0.0.6.dist-info/RECORD
